affinda_v2/__init__.py
affinda_v2/_affinda_api.py
affinda_v2/_configuration.py
affinda_v2/_patch.py
affinda_v2/_vendor.py
affinda_v2/_version.py
affinda_v2/py.typed
affinda_v2/token_credential.py
affinda_v2/aio/__init__.py
affinda_v2/aio/_affinda_api.py
affinda_v2/aio/_configuration.py
affinda_v2/aio/_patch.py
affinda_v2/aio/token_credential.py
affinda_v2/aio/operations/__init__.py
affinda_v2/aio/operations/_affinda_api_operations.py
affinda_v2/aio/operations/_patch.py
affinda_v2/models/__init__.py
affinda_v2/models/_affinda_api_enums.py
affinda_v2/models/_models.py
affinda_v2/models/_models_py3.py
affinda_v2/models/_patch.py
affinda_v2/operations/__init__.py
affinda_v2/operations/_affinda_api_operations.py
affinda_v2/operations/_patch.py
affinda_v2-3.11.1.post3.dist-info/LICENSE
affinda_v2-3.11.1.post3.dist-info/METADATA
affinda_v2-3.11.1.post3.dist-info/WHEEL
affinda_v2-3.11.1.post3.dist-info/top_level.txt
affinda_v2-3.11.1.post3.dist-info/zip-safe
affinda_v2-3.11.1.post3.dist-info/RECORD
