Metadata-Version: 2.1
Name: affinda-v2
Version: 3.11.1.post3
Summary: Client library for the Affinda API
Home-page: https://github.com/affinda/affinda-python
Author: Affinda
Author-email: contact@affinda.com
Maintainer: Affinda
Maintainer-email: contact@affinda.com
License: MIT
Project-URL: Changelog, https://github.com/affinda/affinda-python/blob/stable/CHANGELOG.md
Project-URL: Documentation, https://github.com/affinda/affinda-python/blob/stable/README.md
Project-URL: Source, https://github.com/affinda/affinda-python
Project-URL: Tracker, https://github.com/affinda/affinda-python/issues
Keywords: affinda,api
Classifier: Development Status :: 5 - Production/Stable
Classifier: Intended Audience :: Developers
Classifier: License :: OSI Approved :: MIT License
Classifier: Natural Language :: English
Classifier: Programming Language :: Python
Classifier: Programming Language :: Python :: 3
Classifier: Programming Language :: Python :: 3.6
Classifier: Programming Language :: Python :: 3.7
Classifier: Programming Language :: Python :: 3.8
Classifier: Programming Language :: Python :: 3.9
Classifier: Topic :: Software Development :: Libraries
Requires-Python: >=3.6
License-File: LICENSE
Requires-Dist: azure-core>=1.26.0
Requires-Dist: azure-identity
Requires-Dist: msrest>=0.6.21
Requires-Dist: requests
Provides-Extra: dev
Requires-Dist: black; extra == "dev"
Requires-Dist: check-manifest; extra == "dev"
Requires-Dist: mypy; extra == "dev"
Requires-Dist: tox>=3.3.0; extra == "dev"
Requires-Dist: twine; extra == "dev"
Requires-Dist: types-requests; extra == "dev"
Requires-Dist: wheel; extra == "dev"
